senfd/__init__.py
senfd/cli.py
senfd/errors.py
senfd/pipeline.py
senfd/tables.py
senfd/utils.py
senfd/documents/__init__.py
senfd/documents/base.py
senfd/documents/enriched.py
senfd/documents/plain.py
senfd/schemas/__init__.py
senfd/schemas/enriched.figure.document.schema.json
senfd/schemas/plain.figure.document.schema.json
senfd/templates/__init__.py
senfd/templates/enriched.figure.document.html.jinja2
senfd/templates/plain.figure.document.html.jinja2
senfd-0.2.3.dist-info/LICENSE
senfd-0.2.3.dist-info/METADATA
senfd-0.2.3.dist-info/WHEEL
senfd-0.2.3.dist-info/entry_points.txt
senfd-0.2.3.dist-info/top_level.txt
senfd-0.2.3.dist-info/RECORD
