Metadata-Version: 2.1
Name: senfd
Version: 0.2.3
Summary: Semantic Enhancer for Figure Documents
Author-email: "Simon A. F. Lund" <os@safl.dk>
License: LGPL-2.1-only
License-File: LICENSE
Requires-Dist: jinja2
Requires-Dist: pydantic
Requires-Dist: pytest
Requires-Dist: pytest-cov
Requires-Dist: python-docx
